sigma/backends/logpoint/__init__.py
sigma/backends/logpoint/logpoint.py
sigma/pipelines/logpoint/__init__.py
sigma/pipelines/logpoint/azure.py
sigma/pipelines/logpoint/logpoint_mapping.py
sigma/pipelines/logpoint/m365.py
sigma/pipelines/logpoint/windows.py
pysigma_backend_logpoint-0.4.0.dist-info/METADATA
pysigma_backend_logpoint-0.4.0.dist-info/WHEEL
pysigma_backend_logpoint-0.4.0.dist-info/licenses/LICENSE
pysigma_backend_logpoint-0.4.0.dist-info/RECORD
