Metadata-Version: 2.4
Name: pysigma-backend-logpoint
Version: 0.4.0
Summary: pySigma Logpoint backend
License: LGPL-2.1-only
License-File: LICENSE
Author: Surya Majhi
Author-email: suryamajhi20@gmail.com
Requires-Python: >=3.9,<4.0
Classifier: License :: OSI Approved
Classifier: Programming Language :: Python :: 3
Classifier: Programming Language :: Python :: 3.9
Classifier: Programming Language :: Python :: 3.10
Classifier: Programming Language :: Python :: 3.11
Classifier: Programming Language :: Python :: 3.12
Classifier: Programming Language :: Python :: 3.13
Classifier: Programming Language :: Python :: 3.14
Requires-Dist: pysigma (>=0.11.23,<0.12.0)
Project-URL: Repository, https://github.com/logpoint/pySigma-backend-logpoint
